{
  "id": 25279,
  "isLike": 0,
  "isLikeCount": 0,
  "isCollect": 0,
  "isOrder": 0,
  "cnName": "240810 NII队 《应许之地》剧场公演 三机位",
  "enName": "",
  "contentNumber": "20708343",
  "firstLetter": "snh",
  "fullSpell": "",
  "posterHomePath": "/DATA/video/2023-10-18/1697591972771.jpg",
  "posterListPath": "/DATA/video/2023-10-18/1697591976657.jpg",
  "posterDetailPath": "/DATA/video/2023-10-18/1697591980941.jpg",
  "contentType": 11,
  "category": 2,
  "tagId": "",
  "grade": ".0",
  "classification": 6,
  "lang": -1,
  "cpId": 73,
  "copyrightStart": "2022-05-04 00:00:00",
  "copyrightEnd": "2050-06-30 00:00:00",
  "duration": "02:44:40",
  "videoType": 7,
  "broadcast8Address": "",
  "broadcast4Address": "",
  "broadcast2Address": "",
  "brief": "应许之地",
  "createTime": "2024-08-11 14:30:50",
  "updateTime": "2024-08-12 21:29:01",
  "related": -1,
  "vodId": "",
  "mediaId": "",
  "resourceType": 0,
  "director": "",
  "performer": "",
  "titleLength": "00:00:00",
  "tailLength": "00:00:00",
  "currentNumber": "1",
  "highlight": "",
  "resourcesMediumList": [],
  "previewUrl": "http://ucdn.letinvr.com/yulan/NII.mp4",
  "reserveOne": "",
  "reserveTwo": "/DATA/promotion/2022-06-10/1654827286271.csv",
  "reserveThree": "",
  "liveBroadcastSeats": [
    {
      "id": 22256,
      "videoId": "20708343",
      "liveId": "20708343",
      "seatId": "21289932956",
      "name": "中-MID",
      "sort": 0,
      "createTime": "2024-08-12 21:29:01",
      "updateTime": "2024-08-12 21:29:01",
      "remark": "",
      "liveBroadcastSeatAddressList": [
        {
          "id": 51633,
          "seatId": "21289932956",
          "addressId": "2s2068924703",
          "fileFormat": 3,
          "vrFormat": 7,
          "videoDistinguish": 4,
          "videoRate": 2,
          "productId": -1,
          "address": "http://ucdn.letinvr.com/snhlive/2024-8yue/8k/240810NIImScam.MP4",
          "sort": 0,
          "createTime": "2024-08-12 21:29:01",
          "updateTime": "2024-08-12 21:29:01",
          "remark": "",
          "productInfo": [],
          "videoId": ""
        },
        {
          "id": 51634,
          "seatId": "21289932956",
          "addressId": "2s0595388337",
          "fileFormat": 3,
          "vrFormat": 4,
          "videoDistinguish": 7,
          "videoRate": 2,
          "productId": -1,
          "address": "http://ucdn.letinvr.com/snhlive/2024-8yue/2k-4k/240810NIImScam4k.mp4",
          "sort": 0,
          "createTime": "2024-08-12 21:29:01",
          "updateTime": "2024-08-12 21:29:01",
          "remark": "",
          "productInfo": [],
          "videoId": ""
        },
        {
          "id": 51635,
          "seatId": "21289932956",
          "addressId": "2s7492545271",
          "fileFormat": 3,
          "vrFormat": 4,
          "videoDistinguish": 14,
          "videoRate": 2,
          "productId": -1,
          "address": "http://ucdn.letinvr.com/snhlive/2024-8yue/2k-4k/240810NIImScam2k.mp4",
          "sort": 0,
          "createTime": "2024-08-12 21:29:01",
          "updateTime": "2024-08-12 21:29:01",
          "remark": "",
          "productInfo": [],
          "videoId": ""
        }
      ]
    },
    {
      "id": 22257,
      "videoId": "20708343",
      "liveId": "20708343",
      "seatId": "29370974028",
      "name": "左-LEFT",
      "sort": 1,
      "createTime": "2024-08-12 21:29:01",
      "updateTime": "2024-08-12 21:29:01",
      "remark": "",
      "liveBroadcastSeatAddressList": [
        {
          "id": 51636,
          "seatId": "29370974028",
          "addressId": "2s5312198059",
          "fileFormat": 3,
          "vrFormat": 7,
          "videoDistinguish": 4,
          "videoRate": 2,
          "productId": -1,
          "address": "http://ucdn.letinvr.com/snhlive/2024-8yue/8k/240810NIIlScam.MP4",
          "sort": 0,
          "createTime": "2024-08-12 21:29:01",
          "updateTime": "2024-08-12 21:29:01",
          "remark": "",
          "productInfo": [],
          "videoId": ""
        },
        {
          "id": 51637,
          "seatId": "29370974028",
          "addressId": "2s8211554169",
          "fileFormat": 3,
          "vrFormat": 4,
          "videoDistinguish": 7,
          "videoRate": 2,
          "productId": -1,
          "address": "http://ucdn.letinvr.com/snhlive/2024-8yue/2k-4k/240810NIIlScam4k.mp4",
          "sort": 0,
          "createTime": "2024-08-12 21:29:01",
          "updateTime": "2024-08-12 21:29:01",
          "remark": "",
          "productInfo": [],
          "videoId": ""
        },
        {
          "id": 51638,
          "seatId": "29370974028",
          "addressId": "2s3054677882",
          "fileFormat": 3,
          "vrFormat": 4,
          "videoDistinguish": 14,
          "videoRate": 2,
          "productId": -1,
          "address": "http://ucdn.letinvr.com/snhlive/2024-8yue/2k-4k/240810NIIlScam2k.mp4",
          "sort": 0,
          "createTime": "2024-08-12 21:29:01",
          "updateTime": "2024-08-12 21:29:01",
          "remark": "",
          "productInfo": [],
          "videoId": ""
        }
      ]
    },
    {
      "id": 22258,
      "videoId": "20708343",
      "liveId": "20708343",
      "seatId": "29109302577",
      "name": "右-RIGHT",
      "sort": 2,
      "createTime": "2024-08-12 21:29:01",
      "updateTime": "2024-08-12 21:29:01",
      "remark": "",
      "liveBroadcastSeatAddressList": [
        {
          "id": 51639,
          "seatId": "29109302577",
          "addressId": "2s5259490311",
          "fileFormat": 3,
          "vrFormat": 7,
          "videoDistinguish": 4,
          "videoRate": 2,
          "productId": -1,
          "address": "http://ucdn.letinvr.com/snhlive/2024-8yue/8k/240810NIIrScam.MP4",
          "sort": 0,
          "createTime": "2024-08-12 21:29:01",
          "updateTime": "2024-08-12 21:29:01",
          "remark": "",
          "productInfo": [],
          "videoId": ""
        },
        {
          "id": 51640,
          "seatId": "29109302577",
          "addressId": "2s3689955825",
          "fileFormat": 3,
          "vrFormat": 4,
          "videoDistinguish": 7,
          "videoRate": 2,
          "productId": -1,
          "address": "http://ucdn.letinvr.com/snhlive/2024-8yue/2k-4k/240810NIIrScam4k.mp4",
          "sort": 0,
          "createTime": "2024-08-12 21:29:01",
          "updateTime": "2024-08-12 21:29:01",
          "remark": "",
          "productInfo": [],
          "videoId": ""
        },
        {
          "id": 51641,
          "seatId": "29109302577",
          "addressId": "2s9924228977",
          "fileFormat": 3,
          "vrFormat": 4,
          "videoDistinguish": 14,
          "videoRate": 2,
          "productId": -1,
          "address": "http://ucdn.letinvr.com/snhlive/2024-8yue/2k-4k/240810NIIrScam2k.mp4",
          "sort": 0,
          "createTime": "2024-08-12 21:29:01",
          "updateTime": "2024-08-12 21:29:01",
          "remark": "",
          "productInfo": [],
          "videoId": ""
        }
      ]
    }
  ],
  "csvResultDTOList": []
}