{
  "id": 26079,
  "isLike": 0,
  "isLikeCount": 0,
  "isCollect": 0,
  "isOrder": 0,
  "cnName": "250423 SNH48《头号新闻》新人公演 三机位",
  "enName": "",
  "contentNumber": "23464650",
  "firstLetter": "snh",
  "fullSpell": "",
  "posterHomePath": "/DATA/mmsvideo/2025-03-31/1743396790229.jpg",
  "posterListPath": "/DATA/mmsvideo/2025-03-31/1743396805205.jpg",
  "posterDetailPath": "/DATA/mmsvideo/2025-03-31/1743396822162.jpg",
  "contentType": 11,
  "category": 2,
  "tagId": "",
  "grade": ".0",
  "classification": 1,
  "lang": -1,
  "cpId": 73,
  "copyrightStart": "2022-05-04 00:00:00",
  "copyrightEnd": "2050-06-30 00:00:00",
  "duration": "03:59:14",
  "videoType": 7,
  "broadcast8Address": "",
  "broadcast4Address": "",
  "broadcast2Address": "",
  "brief": "《头号新闻》",
  "createTime": "2025-04-24 09:02:10",
  "updateTime": "2025-04-25 16:18:57",
  "related": -1,
  "vodId": "",
  "mediaId": "",
  "resourceType": 0,
  "director": "",
  "performer": "",
  "titleLength": "00:00:00",
  "tailLength": "00:00:00",
  "currentNumber": "1",
  "highlight": "",
  "resourcesMediumList": [],
  "previewUrl": "http://ucdn.letinvr.com/yulan/HII.mp4",
  "reserveOne": "",
  "reserveTwo": "/DATA/promotion/2022-06-10/1654827286271.csv",
  "reserveThree": "",
  "liveBroadcastSeats": [
    {
      "id": 24725,
      "videoId": "23464650",
      "liveId": "23464650",
      "seatId": "22609011949",
      "name": "中-MID",
      "sort": 0,
      "createTime": "2025-04-25 16:18:57",
      "updateTime": "2025-04-25 16:18:57",
      "remark": "",
      "liveBroadcastSeatAddressList": [
        {
          "id": 58936,
          "seatId": "22609011949",
          "addressId": "2s4521063699",
          "fileFormat": 3,
          "vrFormat": 7,
          "videoDistinguish": 4,
          "videoRate": 2,
          "productId": -1,
          "address": "http://ucdn.letinvr.com/snhlive/2025-4yue/8k/250423SNH48mScam.MP4",
          "sort": 0,
          "createTime": "2025-04-25 16:18:57",
          "updateTime": "2025-04-25 16:18:57",
          "remark": "",
          "productInfo": [],
          "videoId": ""
        },
        {
          "id": 58937,
          "seatId": "22609011949",
          "addressId": "2s1265487587",
          "fileFormat": 3,
          "vrFormat": 4,
          "videoDistinguish": 7,
          "videoRate": 2,
          "productId": -1,
          "address": "http://ucdn.letinvr.com/snhlive/2025-4yue/2k-4k/250423SNH48mScam4k.mp4",
          "sort": 1,
          "createTime": "2025-04-25 16:18:57",
          "updateTime": "2025-04-25 16:18:57",
          "remark": "",
          "productInfo": [],
          "videoId": ""
        },
        {
          "id": 58938,
          "seatId": "22609011949",
          "addressId": "2s3267334269",
          "fileFormat": 3,
          "vrFormat": 4,
          "videoDistinguish": 14,
          "videoRate": 2,
          "productId": -1,
          "address": "http://ucdn.letinvr.com/snhlive/2025-4yue/2k-4k/250423SNH48mScam2k.mp4",
          "sort": 2,
          "createTime": "2025-04-25 16:18:57",
          "updateTime": "2025-04-25 16:18:57",
          "remark": "",
          "productInfo": [],
          "videoId": ""
        }
      ]
    },
    {
      "id": 24726,
      "videoId": "23464650",
      "liveId": "23464650",
      "seatId": "20414415807",
      "name": "左-LEFT",
      "sort": 1,
      "createTime": "2025-04-25 16:18:57",
      "updateTime": "2025-04-25 16:18:57",
      "remark": "",
      "liveBroadcastSeatAddressList": [
        {
          "id": 58939,
          "seatId": "20414415807",
          "addressId": "2s6254066710",
          "fileFormat": 3,
          "vrFormat": 7,
          "videoDistinguish": 4,
          "videoRate": 2,
          "productId": -1,
          "address": "http://ucdn.letinvr.com/snhlive/2025-4yue/8k/250423SNH48lScam.MP4",
          "sort": 0,
          "createTime": "2025-04-25 16:18:57",
          "updateTime": "2025-04-25 16:18:57",
          "remark": "",
          "productInfo": [],
          "videoId": ""
        },
        {
          "id": 58940,
          "seatId": "20414415807",
          "addressId": "2s2389112804",
          "fileFormat": 3,
          "vrFormat": 4,
          "videoDistinguish": 7,
          "videoRate": 2,
          "productId": -1,
          "address": "http://ucdn.letinvr.com/snhlive/2025-4yue/2k-4k/250423SNH48lScam4k.mp4",
          "sort": 1,
          "createTime": "2025-04-25 16:18:57",
          "updateTime": "2025-04-25 16:18:57",
          "remark": "",
          "productInfo": [],
          "videoId": ""
        },
        {
          "id": 58941,
          "seatId": "20414415807",
          "addressId": "2s8641113493",
          "fileFormat": 3,
          "vrFormat": 4,
          "videoDistinguish": 14,
          "videoRate": 2,
          "productId": -1,
          "address": "http://ucdn.letinvr.com/snhlive/2025-4yue/2k-4k/250423SNH48lScam2k.mp4",
          "sort": 2,
          "createTime": "2025-04-25 16:18:57",
          "updateTime": "2025-04-25 16:18:57",
          "remark": "",
          "productInfo": [],
          "videoId": ""
        }
      ]
    },
    {
      "id": 24727,
      "videoId": "23464650",
      "liveId": "23464650",
      "seatId": "26487681810",
      "name": "右-RIGHT",
      "sort": 2,
      "createTime": "2025-04-25 16:18:57",
      "updateTime": "2025-04-25 16:18:57",
      "remark": "",
      "liveBroadcastSeatAddressList": [
        {
          "id": 58942,
          "seatId": "26487681810",
          "addressId": "2s9115536572",
          "fileFormat": 3,
          "vrFormat": 7,
          "videoDistinguish": 4,
          "videoRate": 2,
          "productId": -1,
          "address": "http://ucdn.letinvr.com/snhlive/2025-4yue/8k/250423SNH48rScam.MP4",
          "sort": 0,
          "createTime": "2025-04-25 16:18:57",
          "updateTime": "2025-04-25 16:18:57",
          "remark": "",
          "productInfo": [],
          "videoId": ""
        },
        {
          "id": 58943,
          "seatId": "26487681810",
          "addressId": "2s0265612949",
          "fileFormat": 3,
          "vrFormat": 4,
          "videoDistinguish": 7,
          "videoRate": 2,
          "productId": -1,
          "address": "http://ucdn.letinvr.com/snhlive/2025-4yue/2k-4k/250423SNH48rScam4k.mp4",
          "sort": 1,
          "createTime": "2025-04-25 16:18:57",
          "updateTime": "2025-04-25 16:18:57",
          "remark": "",
          "productInfo": [],
          "videoId": ""
        },
        {
          "id": 58944,
          "seatId": "26487681810",
          "addressId": "2s8971295505",
          "fileFormat": 3,
          "vrFormat": 4,
          "videoDistinguish": 14,
          "videoRate": 2,
          "productId": -1,
          "address": "http://ucdn.letinvr.com/snhlive/2025-4yue/2k-4k/250423SNH48rScam2k.mp4",
          "sort": 2,
          "createTime": "2025-04-25 16:18:57",
          "updateTime": "2025-04-25 16:18:57",
          "remark": "",
          "productInfo": [],
          "videoId": ""
        }
      ]
    }
  ],
  "csvResultDTOList": []
}