{
  "id": 22447,
  "isLike": 0,
  "isLikeCount": 0,
  "isCollect": 0,
  "isOrder": 0,
  "cnName": "230115 SNH48 《春晚特别公演》 三机位",
  "enName": "",
  "contentNumber": "24745395",
  "firstLetter": "X",
  "fullSpell": "",
  "posterHomePath": "/DATA/video/2022-02-18/1645178161665.jpg",
  "posterListPath": "/DATA/video/2022-02-18/1645178356426.jpg",
  "posterDetailPath": "/DATA/video/2022-02-18/1645178359040.jpg",
  "contentType": 11,
  "category": 2,
  "tagId": "",
  "grade": ".0",
  "classification": -1,
  "lang": -1,
  "cpId": 73,
  "copyrightStart": "2022-02-18 00:00:00",
  "copyrightEnd": "2030-03-31 00:00:00",
  "duration": "04:16:54",
  "videoType": 7,
  "broadcast8Address": "http://ucdn.letinvr.com/18612341000/library/2842795283761/230115NewYearmScam.MP4",
  "broadcast4Address": "http://ucdn.letinvr.com/18612341000/library/2842795283761/230115NewYearmScam.MP4",
  "broadcast2Address": "",
  "brief": "SNH",
  "createTime": "2023-01-16 08:46:03",
  "updateTime": "2023-07-28 09:33:40",
  "related": -1,
  "vodId": "",
  "mediaId": "",
  "resourceType": 0,
  "director": "",
  "performer": "",
  "titleLength": "00:00:00",
  "tailLength": "00:00:00",
  "currentNumber": "1",
  "highlight": "",
  "resourcesMediumList": [],
  "previewUrl": "http://ucdn.letinvr.com/yulan/NII.mp4",
  "reserveOne": "",
  "reserveTwo": "",
  "reserveThree": "",
  "liveBroadcastSeats": [
    {
      "id": 10149,
      "videoId": "24745395",
      "liveId": "24745395",
      "seatId": "24183371162",
      "name": "中-MID",
      "sort": 0,
      "createTime": "2023-07-28 09:33:40",
      "updateTime": "2023-07-28 09:33:40",
      "remark": "",
      "liveBroadcastSeatAddressList": [
        {
          "id": 18398,
          "seatId": "24183371162",
          "addressId": "2s5944772412",
          "fileFormat": 3,
          "vrFormat": 7,
          "videoDistinguish": 12,
          "videoRate": 2,
          "productId": -1,
          "address": "http://ucdn.letinvr.com/18612341000/library/2842795283761/230115NewYearmScam.MP4",
          "sort": 0,
          "createTime": "2023-07-28 09:33:40",
          "updateTime": "2023-07-28 09:33:40",
          "remark": "",
          "productInfo": [],
          "videoId": ""
        },
        {
          "id": 18399,
          "seatId": "24183371162",
          "addressId": "2s7446976040",
          "fileFormat": 3,
          "vrFormat": 4,
          "videoDistinguish": 7,
          "videoRate": 2,
          "productId": -1,
          "address": "http://ucdn.letinvr.com/Top50/4k/230115NewYearmScam4k.mp4",
          "sort": 0,
          "createTime": "2023-07-28 09:33:40",
          "updateTime": "2023-07-28 09:33:40",
          "remark": "",
          "productInfo": [],
          "videoId": ""
        },
        {
          "id": 18400,
          "seatId": "24183371162",
          "addressId": "2s9446800618",
          "fileFormat": 3,
          "vrFormat": 4,
          "videoDistinguish": 14,
          "videoRate": 2,
          "productId": -1,
          "address": "http://ucdn.letinvr.com/Top50/2k/230115NewYearmScam2k.mp4",
          "sort": 0,
          "createTime": "2023-07-28 09:33:40",
          "updateTime": "2023-07-28 09:33:40",
          "remark": "",
          "productInfo": [],
          "videoId": ""
        }
      ]
    },
    {
      "id": 10150,
      "videoId": "24745395",
      "liveId": "24745395",
      "seatId": "20388856227",
      "name": "左-LEFT",
      "sort": 1,
      "createTime": "2023-07-28 09:33:40",
      "updateTime": "2023-07-28 09:33:40",
      "remark": "",
      "liveBroadcastSeatAddressList": [
        {
          "id": 18401,
          "seatId": "20388856227",
          "addressId": "2s2643930357",
          "fileFormat": 3,
          "vrFormat": 7,
          "videoDistinguish": 12,
          "videoRate": 2,
          "productId": -1,
          "address": "http://ucdn.letinvr.com/18612341000/library/6325993283761/230115NewYearlScam.MP4",
          "sort": 0,
          "createTime": "2023-07-28 09:33:40",
          "updateTime": "2023-07-28 09:33:40",
          "remark": "",
          "productInfo": [],
          "videoId": ""
        },
        {
          "id": 18402,
          "seatId": "20388856227",
          "addressId": "2s1492846896",
          "fileFormat": 3,
          "vrFormat": 4,
          "videoDistinguish": 7,
          "videoRate": 2,
          "productId": -1,
          "address": "http://ucdn.letinvr.com/Top50/4k/230115NewYearlScam4k.mp4",
          "sort": 0,
          "createTime": "2023-07-28 09:33:40",
          "updateTime": "2023-07-28 09:33:40",
          "remark": "",
          "productInfo": [],
          "videoId": ""
        },
        {
          "id": 18403,
          "seatId": "20388856227",
          "addressId": "2s3351732985",
          "fileFormat": 3,
          "vrFormat": 4,
          "videoDistinguish": 14,
          "videoRate": 2,
          "productId": -1,
          "address": "http://ucdn.letinvr.com/Top50/2k/230115NewYearlScam2k.mp4",
          "sort": 0,
          "createTime": "2023-07-28 09:33:40",
          "updateTime": "2023-07-28 09:33:40",
          "remark": "",
          "productInfo": [],
          "videoId": ""
        }
      ]
    },
    {
      "id": 10151,
      "videoId": "24745395",
      "liveId": "24745395",
      "seatId": "25395756719",
      "name": "右-RIGHT",
      "sort": 2,
      "createTime": "2023-07-28 09:33:40",
      "updateTime": "2023-07-28 09:33:40",
      "remark": "",
      "liveBroadcastSeatAddressList": [
        {
          "id": 18404,
          "seatId": "25395756719",
          "addressId": "2s0161695178",
          "fileFormat": 3,
          "vrFormat": 7,
          "videoDistinguish": 12,
          "videoRate": 2,
          "productId": -1,
          "address": "http://ucdn.letinvr.com/18612341000/library/2548487283761/230115NewYearrScam.MP4",
          "sort": 0,
          "createTime": "2023-07-28 09:33:40",
          "updateTime": "2023-07-28 09:33:40",
          "remark": "",
          "productInfo": [],
          "videoId": ""
        },
        {
          "id": 18405,
          "seatId": "25395756719",
          "addressId": "2s2799632996",
          "fileFormat": 3,
          "vrFormat": 4,
          "videoDistinguish": 7,
          "videoRate": 2,
          "productId": -1,
          "address": "http://ucdn.letinvr.com/Top50/4k/230115NewYearrScam4k.mp4",
          "sort": 1,
          "createTime": "2023-07-28 09:33:40",
          "updateTime": "2023-07-28 09:33:40",
          "remark": "",
          "productInfo": [],
          "videoId": ""
        },
        {
          "id": 18406,
          "seatId": "25395756719",
          "addressId": "2s4783864720",
          "fileFormat": 3,
          "vrFormat": 4,
          "videoDistinguish": 14,
          "videoRate": 2,
          "productId": -1,
          "address": "http://ucdn.letinvr.com/Top50/2k/230115NewYearrScam2k.mp4",
          "sort": 2,
          "createTime": "2023-07-28 09:33:40",
          "updateTime": "2023-07-28 09:33:40",
          "remark": "",
          "productInfo": [],
          "videoId": ""
        }
      ]
    }
  ],
  "csvResultDTOList": [
    {
      "id": 27332,
      "sliceId": "7890a15e59f740de9ab721f0e57b10ae",
      "contentNumber": "24745395",
      "name": "名称",
      "startTime": "00:00:00",
      "endTime": "00:02:00",
      "createTime": "2023-07-28 09:33:40",
      "updateTime": "2023-07-28 09:33:40"
    },
    {
      "id": 27306,
      "sliceId": "8cf67f8a13d4461a838f1984db24b69c",
      "contentNumber": "24745395",
      "name": "P1 第一只兔子",
      "startTime": "0:01:24",
      "endTime": "0:05:05",
      "createTime": "2023-07-28 09:33:40",
      "updateTime": "2023-07-28 09:33:40"
    },
    {
      "id": 27307,
      "sliceId": "66973d0bdff44d10bfdd4f048f618c0f",
      "contentNumber": "24745395",
      "name": "P2 一心向前",
      "startTime": "0:07:40",
      "endTime": "0:10:42",
      "createTime": "2023-07-28 09:33:40",
      "updateTime": "2023-07-28 09:33:40"
    },
    {
      "id": 27308,
      "sliceId": "ba87738693f2490e9cf86228f855dc07",
      "contentNumber": "24745395",
      "name": "P3 我们的风",
      "startTime": "0:11:23",
      "endTime": "0:14:42",
      "createTime": "2023-07-28 09:33:40",
      "updateTime": "2023-07-28 09:33:40"
    },
    {
      "id": 27309,
      "sliceId": "8301716cf0d44278a22bb14ba746e3aa",
      "contentNumber": "24745395",
      "name": "P4 用我的声音",
      "startTime": "0:15:42",
      "endTime": "0:19:16",
      "createTime": "2023-07-28 09:33:40",
      "updateTime": "2023-07-28 09:33:40"
    },
    {
      "id": 27310,
      "sliceId": "97fa1055eb574a26b4dc1573fbdac910",
      "contentNumber": "24745395",
      "name": "P5 加油!S队",
      "startTime": "0:19:53",
      "endTime": "0:22:57",
      "createTime": "2023-07-28 09:33:40",
      "updateTime": "2023-07-28 09:33:40"
    },
    {
      "id": 27311,
      "sliceId": "ae3ca1d1ce03416a87ec4f3d520282a8",
      "contentNumber": "24745395",
      "name": "P6 MC1 对元宇宙的新期待，想在元宇宙里干什么",
      "startTime": "0:23:50",
      "endTime": "0:44:05",
      "createTime": "2023-07-28 09:33:40",
      "updateTime": "2023-07-28 09:33:40"
    },
    {
      "id": 27312,
      "sliceId": "f6f0068b460445388f20e7d8724c333e",
      "contentNumber": "24745395",
      "name": "P7 City Lights",
      "startTime": "0:45:17",
      "endTime": "0:48:22",
      "createTime": "2023-07-28 09:33:40",
      "updateTime": "2023-07-28 09:33:40"
    },
    {
      "id": 27313,
      "sliceId": "7a2bb44a1cd54feba5b7a1b60de9dc43",
      "contentNumber": "24745395",
      "name": "P8 占据",
      "startTime": "0:51:24",
      "endTime": "0:55:47",
      "createTime": "2023-07-28 09:33:40",
      "updateTime": "2023-07-28 09:33:40"
    },
    {
      "id": 27314,
      "sliceId": "ecae4d0547064110b0ce09ebe7116715",
      "contentNumber": "24745395",
      "name": "P9 耳语者",
      "startTime": "0:59:04",
      "endTime": "1:02:34",
      "createTime": "2023-07-28 09:33:40",
      "updateTime": "2023-07-28 09:33:40"
    },
    {
      "id": 27315,
      "sliceId": "cecc852cb67342b1a597556d924b2ae4",
      "contentNumber": "24745395",
      "name": "P10 Heart Beat",
      "startTime": "1:05:17",
      "endTime": "1:09:13",
      "createTime": "2023-07-28 09:33:40",
      "updateTime": "2023-07-28 09:33:40"
    },
    {
      "id": 27316,
      "sliceId": "75064e114b3b426e96df9fb46ed76440",
      "contentNumber": "24745395",
      "name": "P11 零和游戏",
      "startTime": "1:10:23",
      "endTime": "1:14:41",
      "createTime": "2023-07-28 09:33:40",
      "updateTime": "2023-07-28 09:33:40"
    },
    {
      "id": 27317,
      "sliceId": "c0889f35c4054a4f8bf85d48fd923b99",
      "contentNumber": "24745395",
      "name": "P12 MC2 大家一起画",
      "startTime": "1:16:14",
      "endTime": "1:42:06",
      "createTime": "2023-07-28 09:33:40",
      "updateTime": "2023-07-28 09:33:40"
    },
    {
      "id": 27318,
      "sliceId": "3a40245b3349493884602f3ab9263d78",
      "contentNumber": "24745395",
      "name": "P13 魔女的诗篇",
      "startTime": "1:44:49",
      "endTime": "1:50:21",
      "createTime": "2023-07-28 09:33:40",
      "updateTime": "2023-07-28 09:33:40"
    },
    {
      "id": 27319,
      "sliceId": "5ae5e77e657d4cd997b8b07915c92d40",
      "contentNumber": "24745395",
      "name": "P14 触电",
      "startTime": "1:54:43",
      "endTime": "1:58:20",
      "createTime": "2023-07-28 09:33:40",
      "updateTime": "2023-07-28 09:33:40"
    },
    {
      "id": 27320,
      "sliceId": "bf95768c020f4e348ccd928e157597f0",
      "contentNumber": "24745395",
      "name": "P15 水蒸气",
      "startTime": "2:01:25",
      "endTime": "2:07:20",
      "createTime": "2023-07-28 09:33:40",
      "updateTime": "2023-07-28 09:33:40"
    },
    {
      "id": 27321,
      "sliceId": "8e2a062a06c4478482f65b57966df36e",
      "contentNumber": "24745395",
      "name": "P16 能做你的女友吗",
      "startTime": "2:10:00",
      "endTime": "2:14:02",
      "createTime": "2023-07-28 09:33:40",
      "updateTime": "2023-07-28 09:33:40"
    },
    {
      "id": 27322,
      "sliceId": "f8f1494f9d11460aa44af6504589b76d",
      "contentNumber": "24745395",
      "name": "P17 天空信",
      "startTime": "2:15:42",
      "endTime": "2:19:00",
      "createTime": "2023-07-28 09:33:40",
      "updateTime": "2023-07-28 09:33:40"
    },
    {
      "id": 27323,
      "sliceId": "93bb17b378334a2f92820f94de94acc6",
      "contentNumber": "24745395",
      "name": "P18 初眠",
      "startTime": "2:22:36",
      "endTime": "2:26:08",
      "createTime": "2023-07-28 09:33:40",
      "updateTime": "2023-07-28 09:33:40"
    },
    {
      "id": 27324,
      "sliceId": "ccf29998e0f9488c8687e3704acb9bcb",
      "contentNumber": "24745395",
      "name": "P19 MC3 和粉丝之间发生的饭随偶像的事情",
      "startTime": "2:27:22",
      "endTime": "2:47:15",
      "createTime": "2023-07-28 09:33:40",
      "updateTime": "2023-07-28 09:33:40"
    },
    {
      "id": 27325,
      "sliceId": "38b6034fe9ef4d8cb1fc072889eea137",
      "contentNumber": "24745395",
      "name": "P20 Feeling You",
      "startTime": "2:49:40",
      "endTime": "2:52:22",
      "createTime": "2023-07-28 09:33:40",
      "updateTime": "2023-07-28 09:33:40"
    },
    {
      "id": 27326,
      "sliceId": "9a1f89eca4b8461aa24a36da06145d73",
      "contentNumber": "24745395",
      "name": "P21 Sugarfree",
      "startTime": "2:55:19",
      "endTime": "2:57:55",
      "createTime": "2023-07-28 09:33:40",
      "updateTime": "2023-07-28 09:33:40"
    },
    {
      "id": 27327,
      "sliceId": "5605a8a46b76421fa74e2f8b0b014fe5",
      "contentNumber": "24745395",
      "name": "P22 Like A Diamond&合理失控",
      "startTime": "3:04:09",
      "endTime": "3:09:09",
      "createTime": "2023-07-28 09:33:40",
      "updateTime": "2023-07-28 09:33:40"
    },
    {
      "id": 27328,
      "sliceId": "75f0b677efdb4601b06ae1f6506a0af4",
      "contentNumber": "24745395",
      "name": "P23 狼与自尊",
      "startTime": "3:12:22",
      "endTime": "3:15:41",
      "createTime": "2023-07-28 09:33:40",
      "updateTime": "2023-07-28 09:33:40"
    },
    {
      "id": 27329,
      "sliceId": "c9ed848783474b4da185fab79e59eb28",
      "contentNumber": "24745395",
      "name": "P24 Suuuuuper Mario",
      "startTime": "3:19:59",
      "endTime": "3:23:37",
      "createTime": "2023-07-28 09:33:40",
      "updateTime": "2023-07-28 09:33:40"
    },
    {
      "id": 27330,
      "sliceId": "00b5bdb5e6284a3ebf7f37cd3f403a2c",
      "contentNumber": "24745395",
      "name": "P25 MC4 贵妃的纸杯",
      "startTime": "3:24:58",
      "endTime": "3:55:08",
      "createTime": "2023-07-28 09:33:40",
      "updateTime": "2023-07-28 09:33:40"
    },
    {
      "id": 27331,
      "sliceId": "8480c43163644e1e9530fc960435f030",
      "contentNumber": "24745395",
      "name": "P26 小团圆 谢幕 击掌",
      "startTime": "3:57:43",
      "endTime": "4:16:54",
      "createTime": "2023-07-28 09:33:40",
      "updateTime": "2023-07-28 09:33:40"
    }
  ]
}