{
  "id": 21652,
  "isLike": 0,
  "isLikeCount": 0,
  "isCollect": 0,
  "isOrder": 0,
  "cnName": "220618 GNZ48生日公演：曾艾佳《独家》主题生日",
  "enName": "",
  "contentNumber": "28666884",
  "firstLetter": "N",
  "fullSpell": "",
  "posterHomePath": "/DATA/video/2023-10-24/1698112695495.jpg",
  "posterListPath": "/DATA/video/2023-10-24/1698112699373.jpg",
  "posterDetailPath": "/DATA/video/2023-10-24/1698112702683.jpg",
  "contentType": 11,
  "category": 2,
  "tagId": "",
  "grade": ".0",
  "classification": -1,
  "lang": -1,
  "cpId": 73,
  "copyrightStart": "2022-06-19 00:00:00",
  "copyrightEnd": "2033-07-08 00:00:00",
  "duration": "03:27:49",
  "videoType": 7,
  "broadcast8Address": "http://ucdn.letinvr.com/18612341000/library/3954107306561/0618曾.mp4",
  "broadcast4Address": "",
  "broadcast2Address": "",
  "brief": "1",
  "createTime": "2022-06-19 23:02:12",
  "updateTime": "2023-10-24 09:58:33",
  "related": -1,
  "vodId": "",
  "mediaId": "",
  "resourceType": 0,
  "director": "",
  "performer": "",
  "titleLength": "00:00:00",
  "tailLength": "00:00:00",
  "currentNumber": "1",
  "highlight": "",
  "resourcesMediumList": [],
  "previewUrl": "http://ucdn.letinvr.com/yulan/G.mp4",
  "reserveOne": "",
  "reserveTwo": "/DATA/promotion/2022-06-25/1656131870645.csv",
  "reserveThree": "",
  "liveBroadcastSeats": [
    {
      "id": 14313,
      "videoId": "28666884",
      "liveId": "28666884",
      "seatId": "20673225513",
      "name": "GNZ48",
      "sort": 0,
      "createTime": "2023-10-24 09:58:33",
      "updateTime": "2023-10-24 09:58:33",
      "remark": "",
      "liveBroadcastSeatAddressList": [
        {
          "id": 29565,
          "seatId": "20673225513",
          "addressId": "2s6941238464",
          "fileFormat": 4,
          "vrFormat": 7,
          "videoDistinguish": 4,
          "videoRate": 2,
          "productId": -1,
          "address": "http://ucdn.letinvr.com/18612341000/library/3954107306561/0618曾.mp4",
          "sort": 0,
          "createTime": "2023-10-24 09:58:33",
          "updateTime": "2023-10-24 09:58:33",
          "remark": "",
          "productInfo": [],
          "videoId": ""
        },
        {
          "id": 29566,
          "seatId": "20673225513",
          "addressId": "2s8867710281",
          "fileFormat": 3,
          "vrFormat": 4,
          "videoDistinguish": 7,
          "videoRate": 2,
          "productId": -1,
          "address": "http://ucdn.letinvr.com/gnzlive/2022-6yue/0618z%E6%9B%BE4k.mp4",
          "sort": 0,
          "createTime": "2023-10-24 09:58:33",
          "updateTime": "2023-10-24 09:58:33",
          "remark": "",
          "productInfo": [],
          "videoId": ""
        },
        {
          "id": 29567,
          "seatId": "20673225513",
          "addressId": "2s4254194567",
          "fileFormat": 3,
          "vrFormat": 4,
          "videoDistinguish": 14,
          "videoRate": 2,
          "productId": -1,
          "address": "http://ucdn.letinvr.com/gnzlive/2022-6yue/0618z%E6%9B%BE2k.mp4",
          "sort": 0,
          "createTime": "2023-10-24 09:58:33",
          "updateTime": "2023-10-24 09:58:33",
          "remark": "",
          "productInfo": [],
          "videoId": ""
        }
      ]
    }
  ],
  "csvResultDTOList": [
    {
      "id": 34528,
      "sliceId": "c3709bd836304f2984ddddcce0402fa1",
      "contentNumber": "28666884",
      "name": "P1_石中花",
      "startTime": "0:03:09",
      "endTime": "0:07:16",
      "createTime": "2023-10-24 09:58:33",
      "updateTime": "2023-10-24 09:58:33"
    },
    {
      "id": 34529,
      "sliceId": "7b501a16c5ad44d48d88627205f13ef7",
      "contentNumber": "28666884",
      "name": "P2_黑白格子裙",
      "startTime": "0:07:50",
      "endTime": "0:10:55",
      "createTime": "2023-10-24 09:58:33",
      "updateTime": "2023-10-24 09:58:33"
    },
    {
      "id": 34530,
      "sliceId": "e461b823ffe54a3da37e001fea640070",
      "contentNumber": "28666884",
      "name": "P4_MC2假如我是艾佳会怎么做",
      "startTime": "0:12:10",
      "endTime": "0:17:45",
      "createTime": "2023-10-24 09:58:33",
      "updateTime": "2023-10-24 09:58:33"
    },
    {
      "id": 34531,
      "sliceId": "f722f8c5f5574837a670faaebb94abf8",
      "contentNumber": "28666884",
      "name": "P5_Lollipop",
      "startTime": "0:22:30",
      "endTime": "0:26:00",
      "createTime": "2023-10-24 09:58:33",
      "updateTime": "2023-10-24 09:58:33"
    },
    {
      "id": 34532,
      "sliceId": "a2049a5d942c4f8f8091f51e7b099250",
      "contentNumber": "28666884",
      "name": "P6_MC3女团成员有什么才艺",
      "startTime": "0:26:19",
      "endTime": "0:33:00",
      "createTime": "2023-10-24 09:58:33",
      "updateTime": "2023-10-24 09:58:33"
    },
    {
      "id": 34533,
      "sliceId": "8fd70a06a587443fb8de568caaf6caa7",
      "contentNumber": "28666884",
      "name": "P7_猎梦_Blue Rose",
      "startTime": "0:33:13",
      "endTime": "0:39:25",
      "createTime": "2023-10-24 09:58:33",
      "updateTime": "2023-10-24 09:58:33"
    },
    {
      "id": 34534,
      "sliceId": "bef4680c20e74616a56dfb44eadaa28e",
      "contentNumber": "28666884",
      "name": "P8_破茧_The Shadows_渊",
      "startTime": "0:41:47",
      "endTime": "0:54:32",
      "createTime": "2023-10-24 09:58:33",
      "updateTime": "2023-10-24 09:58:33"
    },
    {
      "id": 34535,
      "sliceId": "3cc5dd16dcc44962a72d946dd9e7fe59",
      "contentNumber": "28666884",
      "name": "P9_Hold Me Tight_Miss Victoria_2024年2月29日",
      "startTime": "1:03:34",
      "endTime": "1:18:55",
      "createTime": "2023-10-24 09:58:33",
      "updateTime": "2023-10-24 09:58:33"
    },
    {
      "id": 34536,
      "sliceId": "19f38702b1fc47f1aa02a97f55bab860",
      "contentNumber": "28666884",
      "name": "P10_MC4粉丝生祝VCR_粉丝福利",
      "startTime": "1:19:27",
      "endTime": "1:41:56",
      "createTime": "2023-10-24 09:58:33",
      "updateTime": "2023-10-24 09:58:33"
    },
    {
      "id": 34537,
      "sliceId": "1232f14161f64c628437a8618e4b2c16",
      "contentNumber": "28666884",
      "name": "P11_花之祭_解语者_最美之人_支配人",
      "startTime": "1:44:50",
      "endTime": "2:01:10",
      "createTime": "2023-10-24 09:58:33",
      "updateTime": "2023-10-24 09:58:33"
    },
    {
      "id": 34538,
      "sliceId": "c7d79bab983d457f9fa57663a8b66dbc",
      "contentNumber": "28666884",
      "name": "P12_恋爱告急",
      "startTime": "2:07:54",
      "endTime": "2:12:30",
      "createTime": "2023-10-24 09:58:33",
      "updateTime": "2023-10-24 09:58:33"
    },
    {
      "id": 34539,
      "sliceId": "6bebe8273b36406795febd719cc096f8",
      "contentNumber": "28666884",
      "name": "P13_弹幕_读信",
      "startTime": "2:15:02",
      "endTime": "3:10:25",
      "createTime": "2023-10-24 09:58:33",
      "updateTime": "2023-10-24 09:58:33"
    },
    {
      "id": 34540,
      "sliceId": "87c68cfd00124d54972478f3c4fc5759",
      "contentNumber": "28666884",
      "name": "P14_Happy Rebirthday_Honor_谢幕",
      "startTime": "3:12:29",
      "endTime": "3:25:55",
      "createTime": "2023-10-24 09:58:33",
      "updateTime": "2023-10-24 09:58:33"
    }
  ]
}