{
  "id": 25510,
  "isLike": 0,
  "isLikeCount": 0,
  "isCollect": 0,
  "isOrder": 0,
  "cnName": "240906 SII队《幻境》B版公演 三机位",
  "enName": "",
  "contentNumber": "29987255",
  "firstLetter": "S",
  "fullSpell": "",
  "posterHomePath": "/DATA/video/2023-10-17/1697535937011.jpg",
  "posterListPath": "/DATA/video/2023-10-17/1697535940248.jpg",
  "posterDetailPath": "/DATA/video/2023-10-17/1697535943209.jpg",
  "contentType": 11,
  "category": 2,
  "tagId": "",
  "grade": ".0",
  "classification": 1,
  "lang": -1,
  "cpId": 73,
  "copyrightStart": "2022-02-18 00:00:00",
  "copyrightEnd": "2050-03-31 00:00:00",
  "duration": "03:15:52",
  "videoType": 7,
  "broadcast8Address": "",
  "broadcast4Address": "",
  "broadcast2Address": "",
  "brief": "SII队《幻境》",
  "createTime": "2024-09-07 08:30:06",
  "updateTime": "2024-09-19 10:04:38",
  "related": -1,
  "vodId": "",
  "mediaId": "",
  "resourceType": 0,
  "director": "",
  "performer": "",
  "titleLength": "00:00:00",
  "tailLength": "00:00:00",
  "currentNumber": "1",
  "highlight": "",
  "resourcesMediumList": [],
  "previewUrl": "http://ucdn.letinvr.com/yulan/SII.mp4",
  "reserveOne": "",
  "reserveTwo": "",
  "reserveThree": "",
  "liveBroadcastSeats": [
    {
      "id": 22799,
      "videoId": "29987255",
      "liveId": "29987255",
      "seatId": "25928019887",
      "name": "中-MID",
      "sort": 0,
      "createTime": "2024-09-19 10:04:38",
      "updateTime": "2024-09-19 10:04:38",
      "remark": "",
      "liveBroadcastSeatAddressList": [
        {
          "id": 53244,
          "seatId": "25928019887",
          "addressId": "2s9505844019",
          "fileFormat": 3,
          "vrFormat": 7,
          "videoDistinguish": 4,
          "videoRate": 2,
          "productId": -1,
          "address": "http://ucdn.letinvr.com/snhlive/2024-9yue/8k/240906SIImScam.MP4",
          "sort": 0,
          "createTime": "2024-09-19 10:04:38",
          "updateTime": "2024-09-19 10:04:38",
          "remark": "",
          "productInfo": [],
          "videoId": ""
        },
        {
          "id": 53245,
          "seatId": "25928019887",
          "addressId": "2s5406793332",
          "fileFormat": 3,
          "vrFormat": 4,
          "videoDistinguish": 7,
          "videoRate": 2,
          "productId": -1,
          "address": "http://ucdn.letinvr.com/snhlive/2024-9yue/2k-4k/240906SIImScam4k.mp4",
          "sort": 1,
          "createTime": "2024-09-19 10:04:38",
          "updateTime": "2024-09-19 10:04:38",
          "remark": "",
          "productInfo": [],
          "videoId": ""
        },
        {
          "id": 53246,
          "seatId": "25928019887",
          "addressId": "2s4109619348",
          "fileFormat": 3,
          "vrFormat": 4,
          "videoDistinguish": 14,
          "videoRate": 2,
          "productId": -1,
          "address": "http://ucdn.letinvr.com/snhlive/2024-9yue/2k-4k/240906SIImScam2k.mp4",
          "sort": 2,
          "createTime": "2024-09-19 10:04:38",
          "updateTime": "2024-09-19 10:04:38",
          "remark": "",
          "productInfo": [],
          "videoId": ""
        }
      ]
    },
    {
      "id": 22800,
      "videoId": "29987255",
      "liveId": "29987255",
      "seatId": "26073315124",
      "name": "左-LEFT",
      "sort": 1,
      "createTime": "2024-09-19 10:04:38",
      "updateTime": "2024-09-19 10:04:38",
      "remark": "",
      "liveBroadcastSeatAddressList": [
        {
          "id": 53248,
          "seatId": "26073315124",
          "addressId": "2s5962456854",
          "fileFormat": 3,
          "vrFormat": 4,
          "videoDistinguish": 7,
          "videoRate": 2,
          "productId": -1,
          "address": "http://ucdn.letinvr.com/snhlive/2024-9yue/2k-4k/240906SIIlScam4k.mp4",
          "sort": 0,
          "createTime": "2024-09-19 10:04:38",
          "updateTime": "2024-09-19 10:04:38",
          "remark": "",
          "productInfo": [],
          "videoId": ""
        },
        {
          "id": 53249,
          "seatId": "26073315124",
          "addressId": "2s6967873161",
          "fileFormat": 3,
          "vrFormat": 4,
          "videoDistinguish": 14,
          "videoRate": 2,
          "productId": -1,
          "address": "http://ucdn.letinvr.com/snhlive/2024-9yue/2k-4k/240906SIIlScam2k.mp4",
          "sort": 0,
          "createTime": "2024-09-19 10:04:38",
          "updateTime": "2024-09-19 10:04:38",
          "remark": "",
          "productInfo": [],
          "videoId": ""
        },
        {
          "id": 53247,
          "seatId": "26073315124",
          "addressId": "2s6474130229",
          "fileFormat": 3,
          "vrFormat": 7,
          "videoDistinguish": 4,
          "videoRate": 2,
          "productId": -1,
          "address": "http://ucdn.letinvr.com/snhlive/2024-9yue/8k/240906SIIlScam.MP4",
          "sort": 0,
          "createTime": "2024-09-19 10:04:38",
          "updateTime": "2024-09-19 10:04:38",
          "remark": "",
          "productInfo": [],
          "videoId": ""
        }
      ]
    },
    {
      "id": 22801,
      "videoId": "29987255",
      "liveId": "29987255",
      "seatId": "23794374821",
      "name": "右-RIGHT",
      "sort": 2,
      "createTime": "2024-09-19 10:04:38",
      "updateTime": "2024-09-19 10:04:38",
      "remark": "",
      "liveBroadcastSeatAddressList": [
        {
          "id": 53250,
          "seatId": "23794374821",
          "addressId": "2s0154522885",
          "fileFormat": 3,
          "vrFormat": 7,
          "videoDistinguish": 4,
          "videoRate": 2,
          "productId": -1,
          "address": "http://ucdn.letinvr.com/snhlive/2024-9yue/8k/240906SIIrScam.MP4",
          "sort": 0,
          "createTime": "2024-09-19 10:04:38",
          "updateTime": "2024-09-19 10:04:38",
          "remark": "",
          "productInfo": [],
          "videoId": ""
        },
        {
          "id": 53251,
          "seatId": "23794374821",
          "addressId": "2s7235478766",
          "fileFormat": 3,
          "vrFormat": 4,
          "videoDistinguish": 7,
          "videoRate": 2,
          "productId": -1,
          "address": "http://ucdn.letinvr.com/snhlive/2024-9yue/2k-4k/240906SIIrScam4k.mp4",
          "sort": 1,
          "createTime": "2024-09-19 10:04:38",
          "updateTime": "2024-09-19 10:04:38",
          "remark": "",
          "productInfo": [],
          "videoId": ""
        },
        {
          "id": 53252,
          "seatId": "23794374821",
          "addressId": "2s1782573001",
          "fileFormat": 3,
          "vrFormat": 4,
          "videoDistinguish": 14,
          "videoRate": 2,
          "productId": -1,
          "address": "http://ucdn.letinvr.com/snhlive/2024-9yue/2k-4k/240906SIIrScam2k.mp4",
          "sort": 2,
          "createTime": "2024-09-19 10:04:38",
          "updateTime": "2024-09-19 10:04:38",
          "remark": "",
          "productInfo": [],
          "videoId": ""
        }
      ]
    }
  ],
  "csvResultDTOList": []
}